backup_github/__init__.py
backup_github/backup.py
backup_github/github.py
backup_github/main.py
backup_github/metrics.py
backup_github/parse_args.py
backup_github/utils.py
backup_github_org-1.0.10.dist-info/METADATA
backup_github_org-1.0.10.dist-info/entry_points.txt
backup_github_org-1.0.10.dist-info/WHEEL
backup_github_org-1.0.10.dist-info/RECORD
