Metadata-Version: 2.1
Name: backup-github-org
Version: 1.0.10
Summary: 
Author: Karina5005
Author-email: karinaanisimova23062001@gmail.com
Requires-Python: >=3.8.1,<4.0.0
Classifier: Programming Language :: Python :: 3
Classifier: Programming Language :: Python :: 3.9
Classifier: Programming Language :: Python :: 3.10
Classifier: Programming Language :: Python :: 3.11
Requires-Dist: prometheus_client (>=0.16.0,<0.17.0)
Requires-Dist: requests (>=2.28.2,<3.0.0)
